{
    "form name": "HUMAN IMMUNODEFICIENCY VIRUS (HIV) SCREENING TEST CERTIFICATE",
    "name": "Chris Caj",
    "address": "HIV test 7, 1811, Philippines",
    "age": "30",
    "gender": "M",
    "civil status": "Single",
    "date": "09/30/24",
    "certify name": "Chris Caj",
    "physician": "Physician 1",
    "license number": "12345671",
    "date medical exam": "09/30/23",
    "screening-test-others/specify": "unselected",
    "screening_test_rapid": "selected",
    "screening_test_particle agglutination": "unselected",
    "screening_test_eia/cmia/elfa": "unselected",
    "others/specify": null,
    "result_nonreactive": "selected",
    "result_reactive": "unselected",
    "technologist": "MT 1",
    "hiv cert number": "123456772",
    "expiry date": "01/30/2024",
    "pathologist": "Pathologist 7"
}