{
    "form_name": "MEDICAL CERTIFICATE FOR LANDBASED OVERSEAS WORKERS",
    "last_name": "ESAY",
    "first_name": "JOSEPHINE",
    "mid_name": "MARISOL",
    "age": "28",
    "dob": "17\n02\n1995",
    "place_of_birth": "PANGASINAN",
    "nationality": "FILIPINO",
    "is_male": "unselected",
    "is_female": "selected",
    "is_single": "selected",
    "is_married": "unselected",
    "religion": "METHODIST",
    "address": "567 PALM DRIVE BORGY. PASIG, CEBU CITY, CEBU",
    "passport_num": "197678",
    "destination": "JAPAN",
    "position": "DATA ANALYST",
    "employer": "FUJITSU",
    "hear_yes": "selected",
    "hear_no": "unselected",
    "sight_yes": "selected",
    "sight_no": "unselected",
    "vision_yes": "selected",
    "vision_no": "unselected",
    "psych_test_yes": "selected",
    "psych_test_no": "unselected",
    "suffer_med_con_yes": "unselected",
    "suffer_med_con_no": "selected",
    "is_fit": "selected",
    "is_unfit": "unselected",
    "physician": "DR. OLIVIA MARTINEZ",
    "exam_date": "2023-10-02",
    "med_doctor": "JESSICA SMITH",
    "date_sign": "2023-10-02",
    "issued_date": "2023-10-02",
    "expiration_date": "02/10/2024"
}